oscar_benchmarking/SlurmJobSubmitter.py
oscar_benchmarking/SlurmScriptWriter.py
oscar_benchmarking/__init__.py
oscar_benchmarking/plot_metrics.py
oscar_benchmarking/scrape_metrics_template.py
oscar_benchmarking-0.2.0.dist-info/METADATA
oscar_benchmarking-0.2.0.dist-info/WHEEL
oscar_benchmarking-0.2.0.dist-info/licenses/LICENSE
oscar_benchmarking-0.2.0.dist-info/RECORD
