Metadata-Version: 2.3
Name: oscar_benchmarking
Version: 0.2.0
Summary: A package for submitting benchmarking scripts on OSCAR.
Author-email: Michael Tu <michael_s_tu@brown.edu>, Prithvi Takur <prithvi_thakur@brown.edu>, Ashok Ragavendran <ashok_ragavendran@brown.edu>
License-File: LICENSE
Classifier: License :: OSI Approved :: MIT License
Classifier: Operating System :: OS Independent
Classifier: Programming Language :: Python :: 3
Requires-Python: >=3.9
Requires-Dist: matplotlib>=3.9.1
Requires-Dist: pandas>=2.2.2
Requires-Dist: pytest>=8.2.2
Requires-Dist: pyyaml>=6.0.1
